databricks/__init__.py
databricks/version.py
databricks/rag/__init__.py
databricks/rag/configs.py
databricks/rag/constants.py
databricks/rag/entities.py
databricks/rag/environments.py
databricks/rag/errors.py
databricks/rag/version.py
databricks/rag/evaluation/__init__.py
databricks/rag/evaluation/offline.py
databricks/rag/evaluation/online.py
databricks/rag/scoring/__init__.py
databricks/rag/scoring/feedback.py
databricks/rag/scoring/langchain_tracer.py
databricks/rag/scoring/predictions.py
databricks/rag/scoring/schema_v2.py
databricks/rag/studio/__init__.py
databricks/rag/studio/chain_logging.py
databricks/rag/studio/configs.py
databricks/rag/unpacking/__init__.py
databricks/rag/unpacking/entities.py
databricks/rag/unpacking/job.py
databricks/rag/unpacking/schemas.py
databricks/rag/unpacking/unpack.py
databricks/rag/utils/__init__.py
databricks/rag/utils/mlflow.py
databricks/rag/utils/tables.py
databricks/rag/utils/uc.py
databricks/rag_eval/__init__.py
databricks/rag_eval/_library_version.py
databricks/rag_eval/constants.py
databricks/rag_eval/context.py
databricks/rag_eval/env_vars.py
databricks/rag_eval/clients/__init__.py
databricks/rag_eval/clients/databricks_api_client.py
databricks/rag_eval/clients/llmjudge/__init__.py
databricks/rag_eval/clients/llmjudge/llm_judge_client.py
databricks/rag_eval/clients/llmjudge/proto_serde.py
databricks/rag_eval/clients/llmproxy/__init__.py
databricks/rag_eval/clients/llmproxy/llm_proxy_client.py
databricks/rag_eval/config/__init__.py
databricks/rag_eval/config/assessment_config.py
databricks/rag_eval/config/constants.py
databricks/rag_eval/config/evaluation_config.py
databricks/rag_eval/config/example_config.py
databricks/rag_eval/config/judge_config.py
databricks/rag_eval/evaluation/__init__.py
databricks/rag_eval/evaluation/assessments.py
databricks/rag_eval/evaluation/entities.py
databricks/rag_eval/evaluation/harness.py
databricks/rag_eval/evaluation/metrics.py
databricks/rag_eval/evaluation/models.py
databricks_rag_studio-0.2.0.dist-info/LICENSE.md
databricks_rag_studio-0.2.0.dist-info/METADATA
databricks_rag_studio-0.2.0.dist-info/WHEEL
databricks_rag_studio-0.2.0.dist-info/entry_points.txt
databricks_rag_studio-0.2.0.dist-info/top_level.txt
databricks_rag_studio-0.2.0.dist-info/RECORD
