Metadata-Version: 2.1
Name: databricks-rag-studio
Version: 0.2.0
Summary: Databricks RAG Studio Library
Home-page: UNKNOWN
Author: Databricks
Author-email: feedback@databricks.com
License: Databricks Proprietary License
Platform: UNKNOWN
Classifier: Development Status :: 3 - Alpha
Classifier: License :: Other/Proprietary License
Classifier: Programming Language :: Python :: Implementation :: CPython
Classifier: Programming Language :: Python :: Implementation :: PyPy
Requires-Dist: databricks-sdk (>=0.23.0)
Requires-Dist: mlflow-skinny[databricks]
Requires-Dist: mlflow (>=2.12.2)
Requires-Dist: langchain (>=0.1.12)
Requires-Dist: langchain-core (>=0.1.33)
Requires-Dist: langchain-community (>=0.0.28)
Requires-Dist: databricks-vectorsearch (>=0.26)
Requires-Dist: tiktoken
Requires-Dist: tqdm
Requires-Dist: typing-extensions (>=4.5.0)
Requires-Dist: urllib3 (>=2.0)
